README.txt
setup.py
binarySearchTree/__init__.py
tanujbinarysearchtree.egg-info/PKG-INFO
tanujbinarysearchtree.egg-info/SOURCES.txt
tanujbinarysearchtree.egg-info/dependency_links.txt
tanujbinarysearchtree.egg-info/top_level.txt